[
  {
    "name": "suitwy :/",
    "total": 8,
    "raids": {
      "Garden of Salvation": 8
    },
    "membershipId": "4611686018512060330",
    "membershipType": 2,
    "lastUpdate": "15/04/2026, 18:41:29"
  },
  {
    "name": "Yuu",
    "total": 6,
    "raids": {
      "Vow of the Disciple: Standard": 1,
      "Garden of Salvation": 1,
      "Root of Nightmares: Standard": 1,
      "King's Fall: Standard": 1,
      "Salvation's Edge: Standard": 2
    },
    "membershipId": "4611686018485601045",
    "membershipType": 3,
    "lastUpdate": "15/04/2026, 18:40:41"
  },
  {
    "name": "thechibbis",
    "total": 6,
    "raids": {
      "King's Fall: Standard": 4,
      "Vow of the Disciple: Standard": 1,
      "Root of Nightmares: Standard": 1
    },
    "membershipId": "4611686018478886116",
    "membershipType": 2,
    "lastUpdate": "15/04/2026, 18:40:57"
  },
  {
    "name": "Harvey",
    "total": 2,
    "raids": {
      "Garden of Salvation": 2
    },
    "membershipId": "4611686018428756573",
    "membershipType": 2,
    "lastUpdate": "15/04/2026, 18:41:03"
  },
  {
    "name": "atomz",
    "total": 2,
    "raids": {
      "Root of Nightmares: Standard": 1,
      "King's Fall: Standard": 1
    },
    "membershipId": "4611686018536652590",
    "membershipType": 3,
    "lastUpdate": "15/04/2026, 18:41:08"
  },
  {
    "name": "Cafune",
    "total": 0,
    "raids": {},
    "membershipId": "4611686018532779470",
    "membershipType": 1,
    "lastUpdate": "15/04/2026, 18:40:27"
  },
  {
    "name": "zz",
    "total": 0,
    "raids": {},
    "membershipId": "4611686018554847627",
    "membershipType": 1,
    "lastUpdate": "15/04/2026, 18:40:30"
  },
  {
    "name": "deoxu",
    "total": 0,
    "raids": {},
    "membershipId": "4611686018495018767",
    "membershipType": 3,
    "lastUpdate": "15/04/2026, 18:40:33"
  },
  {
    "name": "bytes",
    "total": 0,
    "raids": {},
    "membershipId": "4611686018468753458",
    "membershipType": 3,
    "lastUpdate": "15/04/2026, 18:40:36"
  },
  {
    "name": "just chill",
    "total": 0,
    "raids": {},
    "membershipId": "4611686018537955341",
    "membershipType": 3,
    "lastUpdate": "15/04/2026, 18:40:37"
  },
  {
    "name": "aycloxz",
    "total": 0,
    "raids": {},
    "membershipId": "4611686018447957458",
    "membershipType": 1,
    "lastUpdate": "15/04/2026, 18:40:39"
  },
  {
    "name": "uremmy",
    "total": 0,
    "raids": {},
    "membershipId": "4611686018462927610",
    "membershipType": 2,
    "lastUpdate": "15/04/2026, 18:40:44"
  },
  {
    "name": "finesya",
    "total": 0,
    "raids": {},
    "membershipId": "4611686018520004201",
    "membershipType": 3,
    "lastUpdate": "15/04/2026, 18:40:46"
  },
  {
    "name": "BMW_M5_V10_S85B50",
    "total": 0,
    "raids": {},
    "membershipId": "4611686018485160172",
    "membershipType": 3,
    "lastUpdate": "15/04/2026, 18:40:49"
  },
  {
    "name": "suitwy :/",
    "total": 0,
    "raids": {},
    "membershipId": "4611686018556709629",
    "membershipType": 1,
    "lastUpdate": "15/04/2026, 18:40:50"
  },
  {
    "name": "johnny ganza",
    "total": 0,
    "raids": {},
    "membershipId": "4611686018515664333",
    "membershipType": 3,
    "lastUpdate": "15/04/2026, 18:40:52"
  },
  {
    "name": "Redacted1512",
    "total": 0,
    "raids": {},
    "membershipId": "4611686018450170758",
    "membershipType": 2,
    "lastUpdate": "15/04/2026, 18:40:55"
  },
  {
    "name": "killanov",
    "total": 0,
    "raids": {},
    "membershipId": "4611686018488837833",
    "membershipType": 3,
    "lastUpdate": "15/04/2026, 18:41:00"
  },
  {
    "name": "Err0r 404 PT",
    "total": 0,
    "raids": {},
    "membershipId": "4611686018433432488",
    "membershipType": 1,
    "lastUpdate": "15/04/2026, 18:41:06"
  },
  {
    "name": "Heartbeats",
    "total": 0,
    "raids": {},
    "membershipId": "4611686018491989083",
    "membershipType": 3,
    "lastUpdate": "15/04/2026, 18:41:11"
  },
  {
    "name": "CãoMonista",
    "total": 0,
    "raids": {},
    "membershipId": "4611686018496636058",
    "membershipType": 1,
    "lastUpdate": "15/04/2026, 18:41:13"
  },
  {
    "name": "XxjowjowxX",
    "total": 0,
    "raids": {},
    "membershipId": "4611686018489160451",
    "membershipType": 3,
    "lastUpdate": "15/04/2026, 18:41:16"
  },
  {
    "name": "Anonyme PT",
    "total": 0,
    "raids": {},
    "membershipId": "4611686018430756006",
    "membershipType": 1,
    "lastUpdate": "15/04/2026, 18:41:20"
  },
  {
    "name": "死の予感",
    "total": 0,
    "raids": {},
    "membershipId": "4611686018485968615",
    "membershipType": 3,
    "lastUpdate": "15/04/2026, 18:41:23"
  },
  {
    "name": "Sennin",
    "total": 0,
    "raids": {},
    "membershipId": "4611686018476765164",
    "membershipType": 3,
    "lastUpdate": "15/04/2026, 18:41:26"
  },
  {
    "name": "sui",
    "total": 0,
    "raids": {},
    "membershipId": "4611686018555996703",
    "membershipType": 6,
    "lastUpdate": "15/04/2026, 18:41:27"
  },
  {
    "name": "Super",
    "total": 0,
    "raids": {},
    "membershipId": "4611686018451070038",
    "membershipType": 2,
    "lastUpdate": "15/04/2026, 18:41:32"
  }
]